csaps/__init__.py
csaps/_base.py
csaps/_reshape.py
csaps/_shortcut.py
csaps/_sspndg.py
csaps/_sspumv.py
csaps/_types.py
csaps/_version.py
csaps/py.typed
csaps-1.3.3.dist-info/LICENSE
csaps-1.3.3.dist-info/METADATA
csaps-1.3.3.dist-info/WHEEL
csaps-1.3.3.dist-info/RECORD
