Metadata-Version: 2.3
Name: csaps
Version: 1.3.3
Summary: Cubic spline approximation (smoothing)
License: MIT
Keywords: cubic,spline,approximation,smoothing,interpolation,csaps
Author: Evgeny Prilepin
Author-email: esp.home@gmail.com
Requires-Python: >=3.10
Classifier: Development Status :: 5 - Production/Stable
Classifier: Intended Audience :: Developers
Classifier: Intended Audience :: Science/Research
Classifier: License :: OSI Approved :: MIT License
Classifier: Programming Language :: Python
Classifier: Programming Language :: Python :: 3
Classifier: Programming Language :: Python :: 3.10
Classifier: Programming Language :: Python :: 3.11
Classifier: Programming Language :: Python :: 3.12
Classifier: Programming Language :: Python :: 3.13
Classifier: Programming Language :: Python :: 3 :: Only
Classifier: Programming Language :: Python :: Implementation :: CPython
Classifier: Topic :: Scientific/Engineering
Classifier: Topic :: Scientific/Engineering :: Mathematics
Classifier: Topic :: Software Development :: Libraries
Requires-Dist: numpy (>=1.26.2) ; python_version >= "3.12"
Requires-Dist: numpy ; python_version < "3.12"
Requires-Dist: scipy (>=1.11.4) ; python_version >= "3.12"
Requires-Dist: scipy ; python_version < "3.12"
Requires-Dist: typing-extensions
Project-URL: Documentation, https://csaps.readthedocs.io
Project-URL: Homepage, https://github.com/espdev/csaps
Project-URL: Repository, https://github.com/espdev/csaps
